databaseds/DataBase.xmi
databaseds/DataBaseds
databaseds/__init__.py
databaseds/_version.py
databaseds/compatibility.py
databaseds/database.py
databaseds/db_errors.py
databaseds/fixtures.py
databaseds/mysql2sqlite.sh
databaseds/db_access/__init__.py
databaseds/db_access/create_db.sql
databaseds/db_access/create_db_tables.sql
databaseds/db_access/sqlite3.py
pytango_db-0.5.1.dist-info/licenses/LICENSE.txt
pytango_db-0.5.1.dist-info/METADATA
pytango_db-0.5.1.dist-info/WHEEL
pytango_db-0.5.1.dist-info/entry_points.txt
pytango_db-0.5.1.dist-info/top_level.txt
pytango_db-0.5.1.dist-info/RECORD
