Metadata-Version: 2.4
Name: pytango-db
Version: 0.5.1
Summary: Fork of PyTango's internal sqlite based database device.
Author-email: MAX IV KITS Software <kits-sw@maxiv.lu.se>
License:                    GNU LESSER GENERAL PUBLIC LICENSE
Project-URL: Repository, https://gitlab.com/tango-controls/incubator/pytango-db
Requires-Python: >=3.6
License-File: LICENSE.txt
Requires-Dist: pytango
Requires-Dist: gevent
Provides-Extra: tests
Requires-Dist: pytest; extra == "tests"
Requires-Dist: psutil; extra == "tests"
Dynamic: license-file
